mesh/__init__.py
mesh/_manylinux.py
mesh/asm/__init__.py
mesh/boost/__init__.py
mesh/boost/contab.py
mesh/boost/disruptor.py
mesh/boost/mooter.py
mesh/boost/remote.py
mesh/boost/ringbuffer.py
mesh/boost/runhook.py
mesh/boost/scheduler.py
mesh/cause/__init__.py
mesh/cause/errors.py
mesh/cause/status.py
mesh/codec/__init__.py
mesh/codec/codec.py
mesh/codec/former.py
mesh/codec/jsons.py
mesh/codec/protobuf.py
mesh/codec/tools.py
mesh/codec/xml.py
mesh/codec/yml.py
mesh/context/__init__.py
mesh/context/context.py
mesh/context/index.py
mesh/context/mesh.py
mesh/context/urn.py
mesh/examples/__init__.py
mesh/examples/consumer.py
mesh/examples/provider.py
mesh/grpx/__init__.py
mesh/grpx/bindservice.py
mesh/grpx/channels.py
mesh/grpx/consumer.py
mesh/grpx/interceptor.py
mesh/grpx/marshaller.py
mesh/grpx/provider.py
mesh/http/__init__.py
mesh/http/consumer.py
mesh/http/provider.py
mesh/log/__init__.py
mesh/log/nop.py
mesh/log/types.py
mesh/macro/__init__.py
mesh/macro/ark.py
mesh/macro/binding.py
mesh/macro/cache.py
mesh/macro/cause.py
mesh/macro/codec.py
mesh/macro/compatible.py
mesh/macro/env.py
mesh/macro/hook.py
mesh/macro/index.py
mesh/macro/inspect.py
mesh/macro/interface.py
mesh/macro/loader.py
mesh/macro/mpi.py
mesh/macro/mps.py
mesh/macro/proxy.py
mesh/macro/spi.py
mesh/macro/types.py
mesh/metrics/__init__.py
mesh/metrics/collector.py
mesh/metrics/scheduler.py
mesh/mpc/__init__.py
mesh/mpc/compiler.py
mesh/mpc/consumer.py
mesh/mpc/consumer_filter.py
mesh/mpc/digest.py
mesh/mpc/eden.py
mesh/mpc/filter.py
mesh/mpc/generic.py
mesh/mpc/inspector.py
mesh/mpc/invoker.py
mesh/mpc/isolate_filter.py
mesh/mpc/mesh_eden.py
mesh/mpc/meshflag.py
mesh/mpc/provider.py
mesh/mpc/provider_filter.py
mesh/mpc/reference.py
mesh/mpc/robust_filter.py
mesh/mpc/service.py
mesh/mpc/service_proxy.py
mesh/mpc/stream.py
mesh/mpc/transporter.py
mesh/psi/__init__.py
mesh/psi/builtin.py
mesh/psi/cache.py
mesh/psi/cipher.py
mesh/psi/cluster.py
mesh/psi/commerce.py
mesh/psi/context.py
daas-0.0.14.dist-info/LICENSE
daas-0.0.14.dist-info/METADATA
daas-0.0.14.dist-info/WHEEL
daas-0.0.14.dist-info/RECORD
