Metadata-Version: 2.3
Name: daas
Version: 0.0.14
Summary: A lightweight, distributed, relational network architecture for MPC.
License: LICENSE
Keywords: servicemesh,rpc,codec,cluster,registry
Author: coyzeng
Author-email: coyzeng@gmail.com
Maintainer: coyzeng
Maintainer-email: coyzeng@gmail.com
Requires-Python: >=3.9,<4.0
Classifier: Development Status :: 5 - Production/Stable
Classifier: License :: OSI Approved :: MIT License
Classifier: License :: Other/Proprietary License
Classifier: Natural Language :: English
Classifier: Operating System :: OS Independent
Classifier: Programming Language :: Python :: 3
Classifier: Programming Language :: Python :: 3.9
Classifier: Programming Language :: Python :: 3.10
Classifier: Programming Language :: Python :: 3.11
Classifier: Programming Language :: Python :: 3.12
Classifier: Programming Language :: Python :: 3.13
Classifier: Topic :: Software Development :: Libraries :: Python Modules
Requires-Dist: aiohttp (>=3.9.5,<4.0.0)
Requires-Dist: grpcio (>=1.71.0,<2.0.0)
Requires-Dist: grpclib (>=0.4.7,<0.5.0)
Requires-Dist: protobuf (>=4.25.3,<5.0.0)
Requires-Dist: requests (>=2.32.3,<3.0.0)
Project-URL: Documentation, https://github.com/jiumi/meio
Project-URL: Homepage, https://github.com/jiumi/meio
Project-URL: Repository, https://github.com/jiumi/meio
